slbs/__init__.py
slbs/__main__.py
slbs/_aws.py
slbs/_gpg.py
slbs/_server.py
slbs/_state.py
slbs/cmdline.py
slbs/resources.py
slbs/upload.py
slbs/builtin_commands/__init__.py
slbs/builtin_commands/_account.py
slbs/builtin_commands/_docker.py
slbs/builtin_commands/_licensing.py
slbs/builtin_commands/_util.py
slbs/builtin_commands/_gpg/Dockerfile
slbs/builtin_commands/_gpg/__init__.py
slbs/builtin_commands/_gpg/genkey.sh
slbs/builtin_commands/_gpg/gpg-agent.conf
slbs/builtin_commands/project_template/src/build/settings/base.json
slbs/builtin_commands/project_template/src/build/settings/linux.json
slbs/builtin_commands/project_template/src/build/settings/mac.json
slbs/builtin_commands/project_template/src/main/icons/Icon.ico
slbs/builtin_commands/project_template/src/main/icons/README.md
slbs/builtin_commands/project_template/src/main/icons/base/16.png
slbs/builtin_commands/project_template/src/main/icons/base/24.png
slbs/builtin_commands/project_template/src/main/icons/base/32.png
slbs/builtin_commands/project_template/src/main/icons/base/48.png
slbs/builtin_commands/project_template/src/main/icons/base/64.png
slbs/builtin_commands/project_template/src/main/icons/linux/1024.png
slbs/builtin_commands/project_template/src/main/icons/linux/128.png
slbs/builtin_commands/project_template/src/main/icons/linux/256.png
slbs/builtin_commands/project_template/src/main/icons/linux/512.png
slbs/builtin_commands/project_template/src/main/icons/mac/1024.png
slbs/builtin_commands/project_template/src/main/icons/mac/128.png
slbs/builtin_commands/project_template/src/main/icons/mac/256.png
slbs/builtin_commands/project_template/src/main/icons/mac/512.png
slbs/builtin_commands/project_template/src/main/python/main.py
slbs/freeze/__init__.py
slbs/freeze/arch.py
slbs/freeze/fedora.py
slbs/freeze/linux.py
slbs/freeze/mac.py
slbs/freeze/ubuntu.py
slbs/freeze/windows.py
slbs/freeze/hooks/__init__.py
slbs/freeze/hooks/hook-PySide2.py
slbs/freeze/hooks/hook-shiboken2.py
slbs-0.0.0.dist-info/LICENSE
slbs-0.0.0.dist-info/METADATA
slbs-0.0.0.dist-info/WHEEL
slbs-0.0.0.dist-info/entry_points.txt
slbs-0.0.0.dist-info/top_level.txt
slbs-0.0.0.dist-info/RECORD
